func2pipe.py
func2pipe/__init__.py
func2pipe/func2pipe.py
func2pipe-0.3.6.dist-info/LICENSE
func2pipe-0.3.6.dist-info/METADATA
func2pipe-0.3.6.dist-info/WHEEL
func2pipe-0.3.6.dist-info/top_level.txt
func2pipe-0.3.6.dist-info/RECORD
