Metadata-Version: 2.1
Name: func2pipe
Version: 0.3.6
Summary: Converts functions into generators
Home-page: UNKNOWN
Author: profesor Hrbolek
Author-email: profesor@hrbolek.cz
License: UNKNOWN
Platform: UNKNOWN
Requires-Python: >=3.5, <4
Requires-Dist: setuptools
